ipca/__init__.py
ipca/ipca.py
ipca/test_ipca.py
ipca-0.6.7.dist-info/LICENSE.md
ipca-0.6.7.dist-info/METADATA
ipca-0.6.7.dist-info/WHEEL
ipca-0.6.7.dist-info/top_level.txt
ipca-0.6.7.dist-info/RECORD
