Metadata-Version: 2.1
Name: ipca
Version: 0.6.7
Summary: Implements the IPCA method of Kelly, Pruitt, Su (2017)
Home-page: https://github.com/bkelly-lab/ipca
Author: Matthias Buechner, Leland Bybee
Author-email: mat.buechner@gmail.com, leland.bybee@gmail.com
License: MIT
Keywords: ipca,regression,IV,instrumental variable
Platform: UNKNOWN
Requires-Dist: numpy
Requires-Dist: progressbar
Requires-Dist: numba
Requires-Dist: scipy
Requires-Dist: joblib
Requires-Dist: scikit-learn
